rtl/riscv_pipeline_top.sv
// -----------------------------------------------------------------------------
// Module      : riscv_pipeline_top
// Description : 5-stage pipelined RV32I processor subset (IF-ID-EX-MEM-WB).
//                Supports: ADD, SUB, AND, OR, XOR, SLT, ADDI, LW, SW, BEQ.
//                Includes:
//                  - EX-stage operand forwarding (from EX/MEM and MEM/WB)
//                  - Load-use hazard detection with 1-cycle stall
//                  - Branch resolution in EX with pipeline flush on taken branch
// Author      : Abhijit Karale
// -----------------------------------------------------------------------------
`timescale 1ns/1ps

module riscv_pipeline_top #(
    parameter IMEM_WORDS = 64,
    parameter DMEM_WORDS = 64
) (
    input  logic clk,
    input  logic rst_n
);

    // ================= Instruction memory =================
    logic [31:0] imem [0:IMEM_WORDS-1];

    // ================= Register file =================
    logic [31:0] regfile [0:31];
    initial begin
        for (int i = 0; i < 32; i++) regfile[i] = 32'd0;
    end

    // ================= Data memory =================
    logic [31:0] dmem [0:DMEM_WORDS-1];
    initial begin
        for (int i = 0; i < DMEM_WORDS; i++) dmem[i] = 32'd0;
    end

    // =====================================================================
    // IF stage
    // =====================================================================
    logic [31:0] pc, pc_next;
    logic        stall;         // load-use hazard stall
    logic        branch_taken;
    logic [31:0] branch_target;

    always_ff @(posedge clk or negedge rst_n) begin
        if (!rst_n) pc <= 32'd0;
        else        pc <= pc_next;
    end

    always_comb begin
        if (branch_taken)      pc_next = branch_target;
        else if (stall)        pc_next = pc;
        else                   pc_next = pc + 32'd4;
    end

    logic [31:0] if_instr;
    assign if_instr = imem[pc[31:2]];

    // IF/ID pipeline register
    logic [31:0] ifid_instr, ifid_pc;
    logic        ifid_bubble;

    always_ff @(posedge clk or negedge rst_n) begin
        if (!rst_n || branch_taken) begin
            ifid_instr  <= 32'd0; // NOP (addi x0,x0,0)
            ifid_pc     <= 32'd0;
        end else if (stall) begin
            // hold current IF/ID contents (bubble inserted downstream instead)
        end else begin
            ifid_instr <= if_instr;
            ifid_pc    <= pc;
        end
    end

    // =====================================================================
    // ID stage
    // =====================================================================
    logic [6:0]  id_opcode;
    logic [4:0]  id_rd, id_rs1, id_rs2;
    logic [2:0]  id_funct3;
    logic [6:0]  id_funct7;
    logic [31:0] id_imm;
    logic        id_reg_write, id_mem_read, id_mem_write, id_mem_to_reg, id_alu_src, id_branch;

    assign id_opcode = ifid_instr[6:0];
    assign id_rd     = ifid_instr[11:7];
    assign id_funct3 = ifid_instr[14:12];
    assign id_rs1    = ifid_instr[19:15];
    assign id_rs2    = ifid_instr[24:20];
    assign id_funct7 = ifid_instr[31:25];

    // Immediate generation (I-type, S-type, B-type)
    always_comb begin
        case (id_opcode)
            7'b0010011, 7'b0000011: // I-type: addi, lw
                id_imm = {{20{ifid_instr[31]}}, ifid_instr[31:20]};
            7'b0100011: // S-type: sw
                id_imm = {{20{ifid_instr[31]}}, ifid_instr[31:25], ifid_instr[11:7]};
            7'b1100011: // B-type: beq
                id_imm = {{19{ifid_instr[31]}}, ifid_instr[31], ifid_instr[7],
                          ifid_instr[30:25], ifid_instr[11:8], 1'b0};
            default:
                id_imm = 32'd0;
        endcase
    end

    // Control decode
    always_comb begin
        id_reg_write  = 1'b0;
        id_mem_read   = 1'b0;
        id_mem_write  = 1'b0;
        id_mem_to_reg = 1'b0;
        id_alu_src    = 1'b0;
        id_branch     = 1'b0;
        case (id_opcode)
            7'b0110011: begin id_reg_write = 1'b1; end                       // R-type
            7'b0010011: begin id_reg_write = 1'b1; id_alu_src = 1'b1; end    // addi
            7'b0000011: begin id_reg_write = 1'b1; id_alu_src = 1'b1;
                               id_mem_read = 1'b1; id_mem_to_reg = 1'b1; end // lw
            7'b0100011: begin id_alu_src = 1'b1; id_mem_write = 1'b1; end    // sw
            7'b1100011: begin id_branch = 1'b1; end                          // beq
            default: ;
        endcase
    end

    // Register file read with write-back same-cycle forwarding (internal bypass)
    logic [4:0]  wb_rd;
    logic        wb_reg_write;
    logic [31:0] wb_data;

    logic [31:0] id_rs1_data, id_rs2_data;
    assign id_rs1_data = (wb_reg_write && wb_rd != 0 && wb_rd == id_rs1) ? wb_data : regfile[id_rs1];
    assign id_rs2_data = (wb_reg_write && wb_rd != 0 && wb_rd == id_rs2) ? wb_data : regfile[id_rs2];

    // =====================================================================
    // Hazard detection unit (load-use hazard) - looks at ID/EX stage
    // =====================================================================
    logic idex_mem_read;
    logic [4:0] idex_rd;

    always_comb begin
        if (idex_mem_read && (idex_rd != 0) &&
            ((idex_rd == id_rs1) || (idex_rd == id_rs2)))
            stall = 1'b1;
        else
            stall = 1'b0;
    end

    // ID/EX pipeline register
    logic [31:0] idex_pc, idex_rs1_data, idex_rs2_data, idex_imm;
    logic [4:0]  idex_rs1, idex_rs2;
    logic [2:0]  idex_funct3;
    logic [6:0]  idex_funct7;
    logic [6:0]  idex_opcode;
    logic        idex_reg_write, idex_mem_write, idex_mem_to_reg, idex_alu_src, idex_branch;

    always_ff @(posedge clk or negedge rst_n) begin
        if (!rst_n || stall || branch_taken) begin
            idex_pc         <= 32'd0;
            idex_rs1_data   <= 32'd0;
            idex_rs2_data   <= 32'd0;
            idex_imm        <= 32'd0;
            idex_rs1        <= 5'd0;
            idex_rs2        <= 5'd0;
            idex_rd         <= 5'd0;
            idex_funct3     <= 3'd0;
            idex_funct7     <= 7'd0;
            idex_opcode     <= 7'd0;
            idex_reg_write  <= 1'b0;
            idex_mem_read   <= 1'b0;
            idex_mem_write  <= 1'b0;
            idex_mem_to_reg <= 1'b0;
            idex_alu_src    <= 1'b0;
            idex_branch     <= 1'b0;
        end else begin
            idex_pc         <= ifid_pc;
            idex_rs1_data   <= id_rs1_data;
            idex_rs2_data   <= id_rs2_data;
            idex_imm        <= id_imm;
            idex_rs1        <= id_rs1;
            idex_rs2        <= id_rs2;
            idex_rd         <= id_rd;
            idex_funct3     <= id_funct3;
            idex_funct7     <= id_funct7;
            idex_opcode     <= id_opcode;
            idex_reg_write  <= id_reg_write;
            idex_mem_read   <= id_mem_read;
            idex_mem_write  <= id_mem_write;
            idex_mem_to_reg <= id_mem_to_reg;
            idex_alu_src    <= id_alu_src;
            idex_branch     <= id_branch;
        end
    end

    // =====================================================================
    // EX stage - forwarding + ALU + branch resolution
    // =====================================================================
    logic [4:0] exmem_rd, memwb_rd;
    logic       exmem_reg_write, memwb_reg_write;
    logic [31:0] exmem_alu_result, memwb_writeback_data;

    logic [1:0] fwd_a_sel, fwd_b_sel; // 00=regfile/idex, 01=EX/MEM, 10=MEM/WB

    always_comb begin
        // Forward A (rs1)
        if (exmem_reg_write && (exmem_rd != 0) && (exmem_rd == idex_rs1))
            fwd_a_sel = 2'b01;
        else if (memwb_reg_write && (memwb_rd != 0) && (memwb_rd == idex_rs1))
            fwd_a_sel = 2'b10;
        else
            fwd_a_sel = 2'b00;

        // Forward B (rs2)
        if (exmem_reg_write && (exmem_rd != 0) && (exmem_rd == idex_rs2))
            fwd_b_sel = 2'b01;
        else if (memwb_reg_write && (memwb_rd != 0) && (memwb_rd == idex_rs2))
            fwd_b_sel = 2'b10;
        else
            fwd_b_sel = 2'b00;
    end

    logic [31:0] ex_operand_a, ex_operand_b_reg, ex_alu_b, ex_alu_result;

    always_comb begin
        case (fwd_a_sel)
            2'b01: ex_operand_a = exmem_alu_result;
            2'b10: ex_operand_a = memwb_writeback_data;
            default: ex_operand_a = idex_rs1_data;
        endcase
        case (fwd_b_sel)
            2'b01: ex_operand_b_reg = exmem_alu_result;
            2'b10: ex_operand_b_reg = memwb_writeback_data;
            default: ex_operand_b_reg = idex_rs2_data;
        endcase
    end

    assign ex_alu_b = idex_alu_src ? idex_imm : ex_operand_b_reg;

    // ALU control: derive operation from opcode/funct3/funct7
    logic [3:0] alu_ctrl;
    always_comb begin
        case (idex_opcode)
            7'b0110011: begin // R-type
                case ({idex_funct7[5], idex_funct3})
                    4'b0_000: alu_ctrl = 4'b0000; // add
                    4'b1_000: alu_ctrl = 4'b0001; // sub
                    4'b0_111: alu_ctrl = 4'b0010; // and
                    4'b0_110: alu_ctrl = 4'b0011; // or
                    4'b0_100: alu_ctrl = 4'b0100; // xor
                    4'b0_010: alu_ctrl = 4'b0101; // slt
                    default:  alu_ctrl = 4'b0000;
                endcase
            end
            7'b0010011: alu_ctrl = 4'b0000; // addi -> add
            7'b0000011: alu_ctrl = 4'b0000; // lw   -> add (base+offset)
            7'b0100011: alu_ctrl = 4'b0000; // sw   -> add (base+offset)
            7'b1100011: alu_ctrl = 4'b0001; // beq  -> sub (for zero compare)
            default:    alu_ctrl = 4'b0000;
        endcase
    end

    always_comb begin
        case (alu_ctrl)
            4'b0000: ex_alu_result = ex_operand_a + ex_alu_b;
            4'b0001: ex_alu_result = ex_operand_a - ex_alu_b;
            4'b0010: ex_alu_result = ex_operand_a & ex_alu_b;
            4'b0011: ex_alu_result = ex_operand_a | ex_alu_b;
            4'b0100: ex_alu_result = ex_operand_a ^ ex_alu_b;
            4'b0101: ex_alu_result = ($signed(ex_operand_a) < $signed(ex_alu_b)) ? 32'd1 : 32'd0;
            default: ex_alu_result = 32'd0;
        endcase
    end

    logic ex_zero;
    assign ex_zero = (ex_operand_a == ex_alu_b);
    assign branch_taken  = idex_branch && ex_zero;
    assign branch_target = idex_pc + idex_imm;

    // EX/MEM pipeline register
    logic [31:0] exmem_store_data, exmem_pc;
    logic        exmem_mem_write, exmem_mem_to_reg;

    always_ff @(posedge clk or negedge rst_n) begin
        if (!rst_n) begin
            exmem_alu_result <= 32'd0;
            exmem_store_data <= 32'd0;
            exmem_rd         <= 5'd0;
            exmem_reg_write  <= 1'b0;
            exmem_mem_write  <= 1'b0;
            exmem_mem_to_reg <= 1'b0;
        end else begin
            exmem_alu_result <= ex_alu_result;
            exmem_store_data <= ex_operand_b_reg;
            exmem_rd         <= idex_rd;
            exmem_reg_write  <= idex_reg_write;
            exmem_mem_write  <= idex_mem_write;
            exmem_mem_to_reg <= idex_mem_to_reg;
        end
    end

    // =====================================================================
    // MEM stage
    // =====================================================================
    logic [31:0] mem_read_data;

    always_ff @(posedge clk) begin
        if (exmem_mem_write)
            dmem[exmem_alu_result[31:2]] <= exmem_store_data;
    end
    assign mem_read_data = dmem[exmem_alu_result[31:2]];

    // MEM/WB pipeline register
    logic [31:0] memwb_alu_result, memwb_mem_data;
    logic        memwb_mem_to_reg;

    always_ff @(posedge clk or negedge rst_n) begin
        if (!rst_n) begin
            memwb_alu_result <= 32'd0;
            memwb_mem_data   <= 32'd0;
            memwb_rd         <= 5'd0;
            memwb_reg_write  <= 1'b0;
            memwb_mem_to_reg <= 1'b0;
        end else begin
            memwb_alu_result <= exmem_alu_result;
            memwb_mem_data   <= mem_read_data;
            memwb_rd         <= exmem_rd;
            memwb_reg_write  <= exmem_reg_write;
            memwb_mem_to_reg <= exmem_mem_to_reg;
        end
    end

    // =====================================================================
    // WB stage
    // =====================================================================
    assign memwb_writeback_data = memwb_mem_to_reg ? memwb_mem_data : memwb_alu_result;
    assign wb_rd        = memwb_rd;
    assign wb_reg_write = memwb_reg_write;
    assign wb_data       = memwb_writeback_data;

    always_ff @(posedge clk) begin
        if (memwb_reg_write && memwb_rd != 0)
            regfile[memwb_rd] <= memwb_writeback_data;
    end

endmodule

tb/tb_riscv_pipeline.sv
// -----------------------------------------------------------------------------
// Testbench   : tb_riscv_pipeline
// Description : Self-checking testbench for the 5-stage pipelined RISC-V
//               processor. Loads imem.hex (assembled by assemble.py), runs
//               the program to completion, then checks final register file
//               and data memory contents against expected values computed
//               by hand for the test program. Also exercises a load-use
//               hazard (stall) and a taken branch (pipeline flush).
// Author      : Abhijit Karale
// -----------------------------------------------------------------------------
`timescale 1ns/1ps

module tb_riscv_pipeline;

    logic clk, rst_n;
    int pass_count = 0;
    int fail_count = 0;

    riscv_pipeline_top dut (.clk(clk), .rst_n(rst_n));

    initial clk = 0;
    always #5 clk = ~clk;

    initial begin
        $readmemh("imem.hex", dut.imem);
    end

    task automatic check_reg(input int idx, input [31:0] expected);
        logic [31:0] actual;
        actual = dut.regfile[idx];
        if (actual === expected) begin
            $display("[PASS] x%0d = 0x%08h (expected 0x%08h)", idx, actual, expected);
            pass_count++;
        end else begin
            $error("[FAIL] x%0d = 0x%08h, expected 0x%08h", idx, actual, expected);
            fail_count++;
        end
    endtask

    task automatic check_mem(input int idx, input [31:0] expected);
        logic [31:0] actual;
        actual = dut.dmem[idx];
        if (actual === expected) begin
            $display("[PASS] mem[%0d] = 0x%08h (expected 0x%08h)", idx, actual, expected);
            pass_count++;
        end else begin
            $error("[FAIL] mem[%0d] = 0x%08h, expected 0x%08h", idx, actual, expected);
            fail_count++;
        end
    endtask

    initial begin
        $dumpfile("waveform/riscv_pipeline.vcd");
        $dumpvars(0, tb_riscv_pipeline);

        $display("=========================================================");
        $display(" 5-Stage Pipelined RISC-V (RV32I subset) Testbench");
        $display("=========================================================");

        rst_n = 0;
        repeat (5) @(posedge clk);
        rst_n = 1;

        // Run enough cycles for the 19-instruction program (including the
        // 1-cycle load-use stall and the branch flush) to fully drain
        // through all 5 pipeline stages.
        repeat (60) @(posedge clk);

        $display("[TEST] Architectural register file check");
        check_reg(1, 32'd5);              // addi x1,x0,5
        check_reg(2, 32'd10);             // addi x2,x0,10
        check_reg(3, 32'd15);             // add  x3,x1,x2
        check_reg(4, 32'd5);              // sub  x4,x2,x1
        check_reg(5, 32'd15);             // lw   x5,0(x0)   <- from sw earlier
        check_reg(6, 32'd20);             // add  x6,x5,x1   <- load-use hazard path
        check_reg(7, 32'd0);              // MUST be 0: flushed by taken branch
        check_reg(8, 32'd42);             // addi x8,x0,42  <- branch target
        check_reg(9, 32'd10);             // and  x9,x3,x2  = 15 & 10
        check_reg(10, 32'd15);            // or   x10,x3,x2 = 15 | 10
        check_reg(11, 32'd5);             // xor  x11,x3,x2 = 15 ^ 10
        check_reg(12, 32'd1);             // slt  x12,x1,x2 = (5<10)

        $display("[TEST] Data memory check");
        check_mem(0, 32'd15);             // sw x3,0(x0) -> mem[0] = 15

        $display("=========================================================");
        $display(" REGRESSION SUMMARY: PASS=%0d  FAIL=%0d", pass_count, fail_count);
        if (fail_count == 0) begin
            $display(" RESULT: ALL TESTS PASSED - pipeline hazards, forwarding,");
            $display("         load-use stall, and branch flush all verified correct");
        end else
            $display(" RESULT: %0d TEST(S) FAILED", fail_count);
        $display("=========================================================");

        $finish;
    end

endmodule

waveform/riscv_pipeline.vcd
$date
	Sun Jul 19 06:11:21 2026
$end
$version
	Icarus Verilog
$end
$timescale
	1ps
$end
$scope module tb_riscv_pipeline $end
$var reg 1 ! clk $end
$var reg 1 " rst_n $end
$var integer 32 # fail_count [31:0] $end
$var integer 32 $ pass_count [31:0] $end
$scope module dut $end
$var wire 1 % branch_taken $end
$var wire 1 ! clk $end
$var wire 32 & if_instr [31:0] $end
$var wire 32 ' mem_read_data [31:0] $end
$var wire 1 " rst_n $end
$var wire 32 ( wb_data [31:0] $end
$var wire 5 ) wb_rd [4:0] $end
$var wire 1 * wb_reg_write $end
$var wire 32 + memwb_writeback_data [31:0] $end
$var wire 32 , id_rs2_data [31:0] $end
$var wire 5 - id_rs2 [4:0] $end
$var wire 32 . id_rs1_data [31:0] $end
$var wire 5 / id_rs1 [4:0] $end
$var wire 5 0 id_rd [4:0] $end
$var wire 7 1 id_opcode [6:0] $end
$var wire 7 2 id_funct7 [6:0] $end
$var wire 3 3 id_funct3 [2:0] $end
$var wire 1 4 ex_zero $end
$var wire 32 5 ex_alu_b [31:0] $end
$var wire 32 6 branch_target [31:0] $end
$var parameter 32 7 DMEM_WORDS $end
$var parameter 32 8 IMEM_WORDS $end
$var reg 4 9 alu_ctrl [3:0] $end
$var reg 32 : ex_alu_result [31:0] $end
$var reg 32 ; ex_operand_a [31:0] $end
$var reg 32 < ex_operand_b_reg [31:0] $end
$var reg 32 = exmem_alu_result [31:0] $end
$var reg 1 > exmem_mem_to_reg $end
$var reg 1 ? exmem_mem_write $end
$var reg 5 @ exmem_rd [4:0] $end
$var reg 1 A exmem_reg_write $end
$var reg 32 B exmem_store_data [31:0] $end
$var reg 2 C fwd_a_sel [1:0] $end
$var reg 2 D fwd_b_sel [1:0] $end
$var reg 1 E id_alu_src $end
$var reg 1 F id_branch $end
$var reg 32 G id_imm [31:0] $end
$var reg 1 H id_mem_read $end
$var reg 1 I id_mem_to_reg $end
$var reg 1 J id_mem_write $end
$var reg 1 K id_reg_write $end
$var reg 1 L idex_alu_src $end
$var reg 1 M idex_branch $end
$var reg 3 N idex_funct3 [2:0] $end
$var reg 7 O idex_funct7 [6:0] $end
$var reg 32 P idex_imm [31:0] $end
$var reg 1 Q idex_mem_read $end
$var reg 1 R idex_mem_to_reg $end
$var reg 1 S idex_mem_write $end
$var reg 7 T idex_opcode [6:0] $end
$var reg 32 U idex_pc [31:0] $end
$var reg 5 V idex_rd [4:0] $end
$var reg 1 W idex_reg_write $end
$var reg 5 X idex_rs1 [4:0] $end
$var reg 32 Y idex_rs1_data [31:0] $end
$var reg 5 Z idex_rs2 [4:0] $end
$var reg 32 [ idex_rs2_data [31:0] $end
$var reg 32 \ ifid_instr [31:0] $end
$var reg 32 ] ifid_pc [31:0] $end
$var reg 32 ^ memwb_alu_result [31:0] $end
$var reg 32 _ memwb_mem_data [31:0] $end
$var reg 1 ` memwb_mem_to_reg $end
$var reg 5 a memwb_rd [4:0] $end
$var reg 1 * memwb_reg_write $end
$var reg 32 b pc [31:0] $end
$var reg 32 c pc_next [31:0] $end
$var reg 1 d stall $end
$scope begin $ivl_for_loop0 $end
$var integer 32 e i [31:0] $end
$upscope $end
$scope begin $ivl_for_loop1 $end
$var integer 32 f i [31:0] $end
$upscope $end
$upscope $end
$scope task check_mem $end
$upscope $end
$scope task check_reg $end
$upscope $end
$upscope $end
$enddefinitions $end
$comment Show the parameter values. $end
$dumpall
b1000000 8
b1000000 7
$end
#0
$dumpvars
b1000000 f
b100000 e
0d
b100 c
b0 b
b0 a
0`
b0 _
b0 ^
b0 ]
b0 \
b0 [
b0 Z
b0 Y
b0 X
0W
b0 V
b0 U
b0 T
0S
0R
0Q
b0 P
b0 O
b0 N
0M
0L
0K
0J
0I
0H
b0 G
0F
0E
b0 D
b0 C
b0 B
0A
b0 @
0?
0>
b0 =
b0 <
b0 ;
b0 :
b0 9
b0 6
b0 5
14
b0 3
b0 2
b0 1
b0 0
b0 /
b0 .
b0 -
b0 ,
b0 +
0*
b0 )
b0 (
b0 '
b10100000000000010010011 &
0%
b0 $
b0 #
0"
0!
$end
#5000
1!
#10000
0!
#15000
1!
#20000
0!
#25000
1!
#30000
0!
#35000
1!
#40000
0!
#45000
1"
1!
#50000
0!
#55000
1E
1K
b1000 c
b101000000000000100010011 &
b101 G
b10011 1
b1 0
b101 -
b100 b
b10100000000000010010011 \
1!
#60000
0!
#65000
b101 :
04
b101 5
b1010 G
b10 0
b1010 -
b1100 c
b1000001000000110110011 &
1L
1W
b10011 T
b1 V
b101 Z
b101 6
b101 P
b100 ]
b101000000000000100010011 \
b1000 b
1!
#70000
0!
#75000
0E
1K
b1010 :
b1000000000100010000001000110011 &
b0 G
b110011 1
b11 0
b1 /
b10 -
b1010 5
b10000 c
b1100 b
b1000 ]
b1000001000000110110011 \
b10 V
b1010 Z
b1010 P
b1110 6
b100 U
1A
b1 @
b101 =
1!
#80000
0!
#85000
b101 ,
b101 ;
b1111 :
b101 (
b101 +
b1010 <
b1 D
b10 C
04
b1010 5
b100 0
b10 /
b1 -
b100000 2
b10100 c
b1100000010000000100011 &
1*
b1 )
b1 a
b101 ^
b10 @
b1010 =
0L
b110011 T
b11 V
b10 Z
b1 X
b0 P
b1000 6
b1000 U
b1100 ]
b1000000000100010000001000110011 \
b10000 b
1!
#90000
0!
#95000
1J
1E
0K
b101 5
b101 :
b0 .
b0 ,
b10001010000011 &
b100011 1
b0 0
b10 3
b0 /
b11 -
b0 2
b1 9
b11000 c
b101 <
04
b1010 ;
b0 D
b1010 (
b1010 +
b10100 b
b10000 ]
b1100000010000000100011 \
b100000 O
b100 V
b1 Z
b10 X
b101 [
b1100 6
b1100 U
b11 @
b1010 B
b1111 =
b10 )
b10 a
b1010 ^
1!
#100000
0!
#105000
b0 :
14
b0 ;
1I
1H
1K
1E
0J
b1111 (
b1111 +
b0 5
b0 9
b10 D
b0 C
b1111 <
b11 1
b101 0
b0 -
b11100 c
b100101000001100110011 &
b11 )
b11 a
b1111 ^
b100 @
b101 B
b101 =
1L
1S
0W
b100011 T
b0 O
b10 N
b0 V
b11 Z
b0 X
b0 [
b10000 6
b10000 U
b10100 ]
b10001010000011 \
b11000 b
1!
#110000
0!
#115000
0E
0I
0H
1K
b101 ,
1d
b100001000010001100011 &
b110011 1
b110 0
b0 3
b101 /
b1 -
b11100 c
b0 <
b0 D
b101 (
b101 +
b11100 b
b11000 ]
b100101000001100110011 \
1R
0S
1Q
1W
b11 T
b101 V
b0 Z
b10100 6
b10100 U
1?
0A
b0 @
b1111 B
b0 =
b100 )
b100 a
b101 ^
1!
#120000
0!
#125000
b100000 c
b0 (
b0 +
0d
b1111 '
0*
b0 )
b0 a
b0 ^
1>
0?
1A
b101 @
b0 B
0L
0R
0Q
0W
b0 T
b0 N
b0 V
b0 6
b0 U
1!
#130000
0!
#135000
1F
0K
b101 .
b101 5
b10100 :
b110001100000000001110010011 &
b1000 G
b1100011 1
b1000 0
b1 /
b101 <
04
b1111 ;
b100100 c
b1111 (
b1111 +
b10 C
b100000 b
b11100 ]
b100001000010001100011 \
1W
b110011 T
b110 V
b1 Z
b101 X
b101 [
b11000 6
b11000 U
0>
0A
b0 @
1`
1*
b101 )
b101 a
b1111 _
1!
#140000
0!
#145000
1%
b0 :
14
b101 ;
1E
1K
0F
b0 .
b1111 ,
b0 (
b0 +
b0 '
b1 9
b0 C
b1100011 G
b10011 1
b111 0
b0 /
b11 -
b11 2
b100100 c
b10101000000000010000010011 &
0`
0*
b0 )
b0 a
1A
b110 @
b101 B
b10100 =
1M
0W
b1100011 T
b1000 V
b1 X
b1000 P
b101 Y
b100100 6
b11100 U
b100000 ]
b110001100000000001110010011 \
b100100 b
1!
#150000
0!
#155000
0E
0K
b0 ,
b0 5
b0 :
b0 G
b0 1
b0 0
b0 -
b0 2
0%
b0 9
b101000 c
b0 <
14
b0 ;
b1111 '
b10100 (
b10100 +
b0 ]
b0 \
0M
b0 T
b0 V
b0 Z
b0 X
b0 P
b0 [
b0 Y
b0 6
b0 U
0A
b1000 @
b0 =
1*
b110 )
b110 a
b0 _
b10100 ^
1!
#160000
0!
#165000
1E
1K
b0 (
b0 +
b101010 G
b10011 1
b1000 0
b1010 -
b1 2
b101100 c
b1000011111010010110011 &
0*
b1000 )
b1000 a
b1111 _
b0 ^
b0 @
b0 B
b100100 ]
b10101000000000010000010011 \
b101000 b
1!
#170000
0!
#175000
0E
1K
b1111 .
b1010 ,
b101010 :
b1000011110010100110011 &
b0 G
b110011 1
b1001 0
b111 3
b11 /
b10 -
b0 2
04
b101010 5
b110000 c
b101100 b
b101000 ]
b1000011111010010110011 \
1L
1W
b10011 T
b1 O
b1000 V
b1010 Z
b101010 P
b1001110 6
b100100 U
b0 )
b0 a
1!
#180000
0!
#185000
b1010 :
b0 '
b10 9
b1010 5
b1010 <
b1111 ;
b1010 0
b110 3
b110100 c
b1000011100010110110011 &
1A
b1000 @
b101010 =
0L
b110011 T
b0 O
b111 N
b1001 V
b10 Z
b11 X
b0 P
b1010 [
b1111 Y
b101000 6
b101000 U
b101100 ]
b1000011110010100110011 \
b110000 b
1!
#190000
0!
#195000
b1111 :
b1000001010011000110011 &
b1011 0
b100 3
b11 9
b111000 c
b101010 (
b101010 +
b110100 b
b110000 ]
b1000011100010110110011 \
b110 N
b1010 V
b101100 6
b101100 U
b1001 @
b1010 B
b1010 =
1*
b1000 )
b1000 a
b0 _
b101010 ^
1!
#200000
0!
#205000
b101 :
b101 .
b1010 (
b1010 +
b100 9
b1100 0
b10 3
b1 /
b111100 c
b10011 &
b1001 )
b1001 a
b1010 ^
b1010 @
b1111 =
b100 N
b1011 V
b110000 6
b110000 U
b110100 ]
b1000001010011000110011 \
b111000 b
1!
#210000
0!
#215000
1E
1K
b0 .
b0 ,
b1 :
b10011 1
b0 0
b0 3
b0 /
b0 -
b101 9
b1000000 c
b101 ;
b1111 (
b1111 +
b111100 b
b111000 ]
b10011 \
b10 N
b1100 V
b1 X
b101 Y
b110100 6
b110100 U
b1011 @
b101 =
b1010 )
b1010 a
b1111 ^
1!
#220000
0!
#225000
b0 :
b101 (
b101 +
b1111 '
14
b0 5
b0 9
b0 <
b0 ;
b1000100 c
b1011 )
b1011 a
b101 ^
b1100 @
b1 =
1L
b10011 T
b0 N
b0 V
b0 Z
b0 X
b0 [
b0 Y
b111000 6
b111000 U
b111100 ]
b1000000 b
1!
#230000
0!
#235000
b1001000 c
b1 (
b1 +
b1000100 b
b1000000 ]
b111100 6
b111100 U
b0 @
b0 B
b0 =
b1100 )
b1100 a
b1111 _
b1 ^
1!
#240000
0!
#245000
b0 (
b0 +
b1001100 c
b0 )
b0 a
b0 ^
b1000000 6
b1000000 U
b1000100 ]
b1001000 b
1!
#250000
0!
#255000
bx &
b1010000 c
b1001100 b
b1001000 ]
b1000100 6
b1000100 U
1!
#260000
0!
#265000
0E
0K
bx .
bx ,
bx 1
bx 0
bx 3
bx /
bx -
bx 2
b1010100 c
b1001000 6
b1001000 U
b1001100 ]
bx \
b1010000 b
1!
#270000
0!
#275000
bx :
bx 5
bx <
x4
bx ;
b1011000 c
b1010100 b
b1010000 ]
0L
0W
bx T
bx O
bx N
bx V
bx Z
bx X
bx [
bx Y
b1001100 6
b1001100 U
1!
#280000
0!
#285000
bx '
b1011100 c
0A
bx @
bx B
bx =
b1010000 6
b1010000 U
b1010100 ]
b1011000 b
1!
#290000
0!
#295000
b1100000 c
bx (
bx +
b1011100 b
b1011000 ]
b1010100 6
b1010100 U
0*
bx )
bx a
bx _
bx ^
1!
#300000
0!
#305000
b1100100 c
b1011000 6
b1011000 U
b1011100 ]
b1100000 b
1!
#310000
0!
#315000
b1101000 c
b1100100 b
b1100000 ]
b1011100 6
b1011100 U
1!
#320000
0!
#325000
b1101100 c
b1100000 6
b1100000 U
b1100100 ]
b1101000 b
1!
#330000
0!
#335000
b1110000 c
b1101100 b
b1101000 ]
b1100100 6
b1100100 U
1!
#340000
0!
#345000
b1110100 c
b1101000 6
b1101000 U
b1101100 ]
b1110000 b
1!
#350000
0!
#355000
b1111000 c
b1110100 b
b1110000 ]
b1101100 6
b1101100 U
1!
#360000
0!
#365000
b1111100 c
b1110000 6
b1110000 U
b1110100 ]
b1111000 b
1!
#370000
0!
#375000
b10000000 c
b1111100 b
b1111000 ]
b1110100 6
b1110100 U
1!
#380000
0!
#385000
b10000100 c
b1111000 6
b1111000 U
b1111100 ]
b10000000 b
1!
#390000
0!
#395000
b10001000 c
b10000100 b
b10000000 ]
b1111100 6
b1111100 U
1!
#400000
0!
#405000
b10001100 c
b10000000 6
b10000000 U
b10000100 ]
b10001000 b
1!
#410000
0!
#415000
b10010000 c
b10001100 b
b10001000 ]
b10000100 6
b10000100 U
1!
#420000
0!
#425000
b10010100 c
b10001000 6
b10001000 U
b10001100 ]
b10010000 b
1!
#430000
0!
#435000
b10011000 c
b10010100 b
b10010000 ]
b10001100 6
b10001100 U
1!
#440000
0!
#445000
b10011100 c
b10010000 6
b10010000 U
b10010100 ]
b10011000 b
1!
#450000
0!
#455000
b10100000 c
b10011100 b
b10011000 ]
b10010100 6
b10010100 U
1!
#460000
0!
#465000
b10100100 c
b10011000 6
b10011000 U
b10011100 ]
b10100000 b
1!
#470000
0!
#475000
b10101000 c
b10100100 b
b10100000 ]
b10011100 6
b10011100 U
1!
#480000
0!
#485000
b10101100 c
b10100000 6
b10100000 U
b10100100 ]
b10101000 b
1!
#490000
0!
#495000
b10110000 c
b10101100 b
b10101000 ]
b10100100 6
b10100100 U
1!
#500000
0!
#505000
b10110100 c
b10101000 6
b10101000 U
b10101100 ]
b10110000 b
1!
#510000
0!
#515000
b10111000 c
b10110100 b
b10110000 ]
b10101100 6
b10101100 U
1!
#520000
0!
#525000
b10111100 c
b10110000 6
b10110000 U
b10110100 ]
b10111000 b
1!
#530000
0!
#535000
b11000000 c
b10111100 b
b10111000 ]
b10110100 6
b10110100 U
1!
#540000
0!
#545000
b11000100 c
b10111000 6
b10111000 U
b10111100 ]
b11000000 b
1!
#550000
0!
#555000
b11001000 c
b11000100 b
b11000000 ]
b10111100 6
b10111100 U
1!
#560000
0!
#565000
b11001100 c
b11000000 6
b11000000 U
b11000100 ]
b11001000 b
1!
#570000
0!
#575000
b11010000 c
b11001100 b
b11001000 ]
b11000100 6
b11000100 U
1!
#580000
0!
#585000
b11010100 c
b11001000 6
b11001000 U
b11001100 ]
b11010000 b
1!
#590000
0!
#595000
b11011000 c
b11010100 b
b11010000 ]
b11001100 6
b11001100 U
1!
#600000
0!
#605000
b11011100 c
b11010000 6
b11010000 U
b11010100 ]
b11011000 b
1!
#610000
0!
#615000
b11100000 c
b11011100 b
b11011000 ]
b11010100 6
b11010100 U
1!
#620000
0!
#625000
b11100100 c
b11011000 6
b11011000 U
b11011100 ]
b11100000 b
1!
#630000
0!
#635000
b11101000 c
b11100100 b
b11100000 ]
b11011100 6
b11011100 U
1!
#640000
0!
#645000
b11101100 c
b11100000 6
b11100000 U
b11100100 ]
b11101000 b
b1101 $
1!
